{
  "db_name": "SQLite",
  "query": "SELECT id, text, done FROM todos ORDER BY time DESC",
  "describe": {
    "columns": [
      {
        "name": "id",
        "ordinal": 0,
        "type_info": "Int64"
      },
      {
        "name": "text",
        "ordinal": 1,
        "type_info": "Text"
      },
      {
        "name": "done",
        "ordinal": 2,
        "type_info": "Bool"
      }
    ],
    "parameters": {
      "Right": 0
    },
    "nullable": [
      false,
      false,
      false
    ]
  },
  "hash": "6f1c753c74c2310cdf247b9b538cc986c3cf4b7d1f09ce0ed14417bfd6a44975"
}
